orbmem/__init__.py
orbmem/core/auth.py
orbmem/core/config.py
orbmem/core/ocdb.py
orbmem/db/mongo.py
orbmem/db/neo4j.py
orbmem/db/postgres.py
orbmem/db/redis.py
orbmem/engines/base_engine.py
orbmem/engines/graph/neo4j_backend.py
orbmem/engines/memory/postgres_backend.py
orbmem/engines/memory/redis_backend.py
orbmem/engines/safety/mongo_backend.py
orbmem/engines/safety/sqlite_safety_backend.py
orbmem/engines/safety/timeseries_backend.py
orbmem/engines/vector/FIASS_backend.py
orbmem/examples/demo.py
orbmem/models/__init__.py
orbmem/models/fingerprints.py
orbmem/models/memory.py
orbmem/models/safety.py
orbmem/utils/embeddings.py
orbmem/utils/exceptions.py
orbmem/utils/helpers.py
orbmem/utils/logger.py
orbmem/utils/validators.py
orbmem-1.1.2.dist-info/licenses/LICENSE
orbmem-1.1.2.dist-info/METADATA
orbmem-1.1.2.dist-info/WHEEL
orbmem-1.1.2.dist-info/top_level.txt
orbmem-1.1.2.dist-info/RECORD
