Metadata-Version: 2.4
Name: orbmem
Version: 1.1.2
Summary: OrbMem – A lightweight Cognitive Memory & Vector framework (Memory, Vectors, Graph, Safety).
Author-email: Tetala Lakshmi Abhishek Reddy <tetalaharitha@gmail.com>
License: MIT License
Project-URL: Homepage, https://github.com/abhis-byte/orbynt-database-OrbMem
Project-URL: Documentation, https://github.com/abhis-byte/orbynt-database-OrbMem
Project-URL: Source, https://github.com/abhis-byte/orbynt-database-OrbMem
Project-URL: Issues, https://github.com/abhis-byte/orbynt-database-OrbMem/issues
Keywords: ai,database,vector,memory,agents,cognitive-db,orbmem
Classifier: Development Status :: 4 - Beta
Classifier: Programming Language :: Python :: 3
Classifier: Programming Language :: Python :: 3 :: Only
Classifier: License :: OSI Approved :: MIT License
Classifier: Operating System :: OS Independent
Classifier: Topic :: Scientific/Engineering :: Artificial Intelligence
Requires-Python: >=3.8
License-File: LICENSE
Requires-Dist: numpy
Requires-Dist: faiss-cpu
Requires-Dist: networkx
Requires-Dist: pymongo
Requires-Dist: python-dotenv
Requires-Dist: pydantic
Dynamic: license-file
